file_stats/__init__.py
file_stats/main.py
file_stats/output.py
file_stats/stats.py
py_file_stats-0.1.0.dist-info/METADATA
py_file_stats-0.1.0.dist-info/WHEEL
py_file_stats-0.1.0.dist-info/entry_points.txt
py_file_stats-0.1.0.dist-info/RECORD
