Metadata-Version: 2.1
Name: py-file-stats
Version: 0.1.0
Summary: A CLI tool that collects statistics about the types of file extensions found in a given directory
License: MIT
Author: cameronhelsby
Author-email: cameron@autone.io
Requires-Python: >=3.13,<3.14
Classifier: License :: OSI Approved :: MIT License
Classifier: Programming Language :: Python :: 3
Classifier: Programming Language :: Python :: 3.13
Requires-Dist: typer (==0.15.2)
